django_textbus/__init__.py
django_textbus/apps.py
django_textbus/conf.py
django_textbus/fields.py
django_textbus/version.py
django_textbus/widgets.py
django_textbus/management/__init__.py
django_textbus/management/commands/__init__.py
django_textbus/management/commands/install_textbus.py
django_textbus/static/django_textbus/js/textbus-init.js
django_textbus/templates/django_textbus/widget.html
django_textbus/templatetags/__init__.py
django_textbus/templatetags/textbus_tags.py
django_textbus/tests/__init__.py
django_textbus/tests/conftest.py
django_textbus/tests/settings.py
django_textbus/tests/test_textbus.py
django_textbus-0.3.3.dist-info/licenses/LICENSE
django_textbus-0.3.3.dist-info/METADATA
django_textbus-0.3.3.dist-info/WHEEL
django_textbus-0.3.3.dist-info/top_level.txt
django_textbus-0.3.3.dist-info/RECORD
